README.rst
pynsca.py
setup.py
pynsca.egg-info/PKG-INFO
pynsca.egg-info/SOURCES.txt
pynsca.egg-info/dependency_links.txt
pynsca.egg-info/not-zip-safe
pynsca.egg-info/top_level.txt